setup.py
Desks.egg-info/PKG-INFO
Desks.egg-info/SOURCES.txt
Desks.egg-info/dependency_links.txt
Desks.egg-info/entry_points.txt
Desks.egg-info/top_level.txt
rest/__init__.py
rest/api.py
rest/config.ini
rest/common/__init__.py
rest/common/auth.py
rest/common/utils.py
rest/resources/__init__.py
rest/resources/document.py
rest/resources/schema.py
rest/resources/search.py
rest/resources/token.py