Metadata-Version: 1.1
Name: Desks
Version: 0.1.4
Summary: Desks to manage and drive Shelf, and provide API and data to the world
Home-page: https://git.leloop.org/broadcast-system/desks
Author: Okhin
Author-email: okhin@okhin.fr
License: UNKNOWN
Platform: UNKNOWN
Requires: flask_restful
Requires: filemagic
Requires: shelves
Requires: itsdangerous
